xextract/__init__.py
xextract/parsers.py
xextract/quantity.py
xextract/extractors/__init__.py
xextract/extractors/extractor_list.py
xextract/extractors/lxml_extractor.py
xextract-0.1.8.dist-info/LICENSE
xextract-0.1.8.dist-info/METADATA
xextract-0.1.8.dist-info/WHEEL
xextract-0.1.8.dist-info/top_level.txt
xextract-0.1.8.dist-info/RECORD
