Metadata-Version: 2.1
Name: xextract
Version: 0.1.8
Summary: Extract structured data from HTML and XML documents like a boss.
Home-page: https://github.com/Mimino666/python-xextract
Author: Michal "Mimino" Danilak
Author-email: michal.danilak@gmail.com
License: MIT
Keywords: HTML parse parsing extraction extract crawl
Platform: UNKNOWN
Classifier: Development Status :: 4 - Beta
Classifier: Intended Audience :: Developers
Classifier: Natural Language :: English
Classifier: License :: OSI Approved :: MIT License
Classifier: Programming Language :: Python
Classifier: Programming Language :: Python :: 2.6
Classifier: Programming Language :: Python :: 2.7
Classifier: Programming Language :: Python :: 3
Classifier: Programming Language :: Python :: 3.3
Classifier: Programming Language :: Python :: 3.5
Classifier: Programming Language :: Python :: 3.6
Classifier: Programming Language :: Python :: 3.7
Classifier: Programming Language :: Python :: 3.8
Classifier: Programming Language :: Python :: Implementation :: CPython
